hello/__init__.py
hello/hello.py
myhellopkg3-0.0.3.dist-info/METADATA
myhellopkg3-0.0.3.dist-info/WHEEL
myhellopkg3-0.0.3.dist-info/top_level.txt
myhellopkg3-0.0.3.dist-info/RECORD
