Metadata-Version: 2.1
Name: myhellopkg3
Version: 0.0.3
Summary: Initial Hello world
Home-page: UNKNOWN
Author: Muthukumar
Author-email: <gkmuthu@gmail.com>
License: UNKNOWN
Keywords: python,video,stream,video stream,camera stream,sockets
Platform: UNKNOWN
Classifier: Development Status :: 1 - Planning
Classifier: Intended Audience :: Developers
Classifier: Programming Language :: Python :: 3
Classifier: Operating System :: Unix
Classifier: Operating System :: MacOS :: MacOS X
Classifier: Operating System :: Microsoft :: Windows
Requires-Dist: pysmb
